genderizer3/__init__.py
genderizer3/cachedModel.py
genderizer3/classifier.py
genderizer3/genderizer3.py
genderizer3/memcachedNamesCollection.py
genderizer3/mongoNamesCollection.py
genderizer3/namesCollection.py
genderizer3/tokenizer.py
genderizer3/trainedData.py
genderizer3/trainer.py
genderizer3/data/__init__.py
genderizer3/data/model_en.json
genderizer3/data/model_en.txt
genderizer3/data/model_en.txt.orig
genderizer3/data/model_en_updated.txt
genderizer3/data/model_generator.py
genderizer3/data/model_tr.txt
genderizer3/data/name_gender.csv
genderizer3/data/updatemodel.py
genderizer3-0.1.2.7.dist-info/LICENSE
genderizer3-0.1.2.7.dist-info/METADATA
genderizer3-0.1.2.7.dist-info/WHEEL
genderizer3-0.1.2.7.dist-info/top_level.txt
genderizer3-0.1.2.7.dist-info/RECORD
