Metadata-Version: 2.1
Name: genderizer3
Version: 0.1.2.7
Summary: Genderizer tries to infer gender information looking at first name and/or making text analysis
License: MIT
Platform: any
License-File: LICENSE
